swimbundle_utils/__init__.py
swimbundle_utils/asset_debugger.py
swimbundle_utils/exceptions.py
swimbundle_utils/flattener.py
swimbundle_utils/helpers.py
swimbundle_utils/ioc.py
swimbundle_utils/rest.py
swimbundle_utils/validation.py
swimbundle_utils/data/tld_list.json
swimbundle_utils-4.8.1.dist-info/METADATA
swimbundle_utils-4.8.1.dist-info/WHEEL
swimbundle_utils-4.8.1.dist-info/top_level.txt
swimbundle_utils-4.8.1.dist-info/RECORD
