Metadata-Version: 2.1
Name: swimbundle-utils
Version: 4.8.1
Summary: Swimlane Bundle Utilities Package
Home-page: UNKNOWN
Author: Swimlane
Author-email: info@swimlane.com
License: UNKNOWN
Keywords: utilities,dictionary,rest
Platform: UNKNOWN
Classifier: Programming Language :: Python :: 3
Requires-Dist: requests (==2.26.0)
Requires-Dist: polling (==0.3.0)
Requires-Dist: six (==1.13.0)
Requires-Dist: validators (==0.14.0)
Requires-Dist: pendulum (==2.1.2)
Requires-Dist: dict-plus (==0.2.3)
Requires-Dist: future (==0.18.2)
Requires-Dist: python-libpython-debian-bin (==0.0.4)
Requires-Dist: ipaddress (==1.0.23)
Requires-Dist: iocextract (==1.13.1)
Requires-Dist: pyparsing (==2.4.7)
